{
    "packages": [
      {
        "name": "razerduino_test",
        "maintainer": "DarkMetalMouse_edit",
        "websiteURL": "https://github.com/Chrisvass/razerduino",
        "email": "",
        "platforms": [
          {
            "name": "razerduino_test1",
            "architecture": "avr",
            "version": "0.9.0",
            "category": "Contributed",
            "url": "https://github.com/Chrisvass/razerduino/blob/master/razerduino-0.9.0.zip?raw=true",
            "archiveFileName": "razerduino-0.9.0.zip",
            "checksum": "SHA-256:DE9D4587F3DF5095AD23D7B7A9272D977423AAC6C55981A3F72B61ABFB16B1B2",
            "size": "5764864",
            "boards": [
              {"name": "microrazer_test1"}
            ],
            "toolsDependencies": [

                { "packager": "arduino", "name": "avr-gcc", "version": "7.3.0-atmel3.6.1-arduino7" },
                { "packager": "arduino", "name": "avrdude", "version": "6.3.0-arduino17" }
            ]
          }
        ],
        "tools": []
      }
    ]
  }
